[
  {
    "discordUserId": "100000000000000000",
    "label": "staging-super-admin",
    "username": "staging-super-admin",
    "globalName": "Staging Super Admin",
    "locale": "de",
    "mode": "VETERAN",
    "isAdmin": true,
    "isSuperAdmin": true,
    "guildId": "900000000000000000",
    "roleIds": [],
    "introCompleted": true,
    "lastSolvedDay": 24,
    "lastSolvedAtDaysAgo": 1,
    "lastLoginAtDaysAgo": 0
  },
  {
    "discordUserId": "200000000000000000",
    "label": "staging-admin",
    "username": "staging-admin",
    "globalName": "Staging Admin",
    "locale": "de",
    "mode": "VETERAN",
    "isAdmin": true,
    "guildId": "900000000000000000",
    "roleIds": [],
    "introCompleted": true,
    "lastSolvedDay": 12,
    "lastSolvedAtDaysAgo": 2,
    "lastLoginAtDaysAgo": 1
  },
  {
    "discordUserId": "300000000000000000",
    "label": "staging-qa-user",
    "locale": "en",
    "mode": "NORMAL",
    "guildId": "900000000000000000",
    "roleIds": ["900000000000000001"],
    "introCompleted": true,
    "lastSolvedDay": 3,
    "lastSolvedAtDaysAgo": 10
  },
  {
    "discordUserId": "300000000000000001",
    "label": "staging-eligible-early",
    "username": "staging-eligible-early",
    "globalName": "Staging Eligible Early",
    "locale": "en",
    "mode": "NORMAL",
    "guildId": "900000000000000000",
    "roleIds": ["900000000000000001"],
    "introCompleted": true,
    "lastSolvedDay": 1,
    "lastSolvedAtDaysAgo": 20,
    "lastLoginAtDaysAgo": 2
  },
  {
    "discordUserId": "300000000000000002",
    "label": "staging-eligible-complete",
    "username": "staging-eligible-complete",
    "globalName": "Staging Eligible Complete",
    "locale": "de",
    "mode": "VETERAN",
    "guildId": "900000000000000000",
    "roleIds": ["900000000000000001"],
    "introCompleted": true,
    "lastSolvedDay": 24,
    "lastSolvedAtDaysAgo": 1,
    "lastLoginAtDaysAgo": 0
  },
  {
    "discordUserId": "300000000000000003",
    "label": "staging-ineligible-missing-role",
    "username": "staging-ineligible-missing-role",
    "globalName": "Staging Ineligible Missing Role",
    "locale": "en",
    "mode": "NORMAL",
    "guildId": "900000000000000000",
    "roleIds": [],
    "introCompleted": true,
    "lastSolvedDay": 5,
    "lastSolvedAtDaysAgo": 5,
    "lastLoginAtDaysAgo": 1
  },
  {
    "discordUserId": "300000000000000004",
    "label": "staging-ineligible-other-role",
    "username": "staging-ineligible-other-role",
    "globalName": "Staging Ineligible Other Role",
    "locale": "de",
    "mode": "NORMAL",
    "guildId": "900000000000000000",
    "roleIds": ["900000000000000002"],
    "introCompleted": true,
    "lastSolvedDay": 7,
    "lastSolvedAtDaysAgo": 3,
    "lastLoginAtDaysAgo": 1
  },
  {
    "discordUserId": "300000000000000005",
    "label": "staging-ineligible-no-intro",
    "username": "staging-ineligible-no-intro",
    "globalName": "Staging Ineligible No Intro",
    "locale": "en",
    "mode": "NORMAL",
    "guildId": "900000000000000000",
    "roleIds": ["900000000000000001"],
    "introCompleted": false,
    "lastSolvedDay": 0,
    "lastLoginAtDaysAgo": 4
  },
  {
    "discordUserId": "300000000000000006",
    "label": "staging-complete-normal-1",
    "username": "staging-complete-normal-1",
    "globalName": "Staging Complete Normal 1",
    "locale": "en",
    "mode": "NORMAL",
    "guildId": "900000000000000000",
    "roleIds": ["900000000000000001"],
    "introCompleted": true,
    "lastSolvedDay": 24,
    "lastSolvedAtDaysAgo": 1,
    "lastLoginAtDaysAgo": 0
  },
  {
    "discordUserId": "300000000000000007",
    "label": "staging-complete-normal-2",
    "username": "staging-complete-normal-2",
    "globalName": "Staging Complete Normal 2",
    "locale": "de",
    "mode": "NORMAL",
    "guildId": "900000000000000000",
    "roleIds": ["900000000000000001"],
    "introCompleted": true,
    "lastSolvedDay": 24,
    "lastSolvedAtDaysAgo": 2,
    "lastLoginAtDaysAgo": 1
  },
  {
    "discordUserId": "300000000000000008",
    "label": "staging-complete-veteran-1",
    "username": "staging-complete-veteran-1",
    "globalName": "Staging Complete Veteran 1",
    "locale": "en",
    "mode": "VETERAN",
    "guildId": "900000000000000000",
    "roleIds": ["900000000000000001"],
    "introCompleted": true,
    "lastSolvedDay": 24,
    "lastSolvedAtDaysAgo": 1,
    "lastLoginAtDaysAgo": 0
  },
  {
    "discordUserId": "300000000000000009",
    "label": "staging-complete-veteran-2",
    "username": "staging-complete-veteran-2",
    "globalName": "Staging Complete Veteran 2",
    "locale": "de",
    "mode": "VETERAN",
    "guildId": "900000000000000000",
    "roleIds": ["900000000000000001"],
    "introCompleted": true,
    "lastSolvedDay": 24,
    "lastSolvedAtDaysAgo": 3,
    "lastLoginAtDaysAgo": 2
  }
]
